helloweb3/__init__.py
helloweb3/actions.py
helloweb3/anvil.py
helloweb3/base.py
helloweb3/connection.py
helloweb3/pow.py
helloweb3/pwn.py
helloweb3/rpc_proxy.py
helloweb3/internal/util.py
helloweb3-0.1.0.dist-info/METADATA
helloweb3-0.1.0.dist-info/WHEEL
helloweb3-0.1.0.dist-info/licenses/LICENSE
helloweb3-0.1.0.dist-info/RECORD
