Metadata-Version: 2.3
Name: helloweb3
Version: 0.1.0
Summary: capture-the-flag framework for web 3
Project-URL: Homepage, https://github.com/bbjubjub2494/helloweb3
Project-URL: Issues, https://github.com/bbjubjub2494/helloweb3/issues
Author-email: "Julie B." <no-reply@bbjubjub.fr>
License-File: LICENSE
Classifier: License :: OSI Approved :: MIT License
Classifier: Operating System :: OS Independent
Classifier: Programming Language :: Python :: 3
Requires-Python: >=3.11
Requires-Dist: eth-abi==5.0.0
Requires-Dist: eth-account==0.10.0
Requires-Dist: web3==6.18.0
